dataframing/__init__.py
dataframing/io.py
dataframing/protocols.py
dataframing/transform.py
dataframing/testsuite/test_transform.py
dataframing-0.1rc2.dist-info/LICENSE
dataframing-0.1rc2.dist-info/METADATA
dataframing-0.1rc2.dist-info/WHEEL
dataframing-0.1rc2.dist-info/top_level.txt
dataframing-0.1rc2.dist-info/RECORD
