Metadata-Version: 2.1
Name: dataframing
Version: 0.1rc2
Summary: Useful functions, classes and tools for handling and interacting with dataframes.
Author-email: "Hernan E. Grecco" <hernan.grecco@gmail.com>
License: BSD-3-Clause
Project-URL: Homepage, https://github.com/hgrecco/dataframing
Project-URL: Bug Tracker, https://github.com/hgrecco/dataframing/issues
Classifier: Development Status :: 4 - Beta
Classifier: Intended Audience :: Developers
Classifier: License :: OSI Approved :: BSD License
Classifier: Operating System :: MacOS :: MacOS X
Classifier: Operating System :: Microsoft :: Windows
Classifier: Operating System :: POSIX
Classifier: Operating System :: OS Independent
Classifier: Programming Language :: Python
Classifier: Topic :: Software Development :: Libraries
Classifier: Topic :: Text Processing
Classifier: Intended Audience :: Science/Research
Classifier: Topic :: Scientific/Engineering
Classifier: Intended Audience :: Developers
Classifier: Programming Language :: Python :: 3.10
Classifier: Programming Language :: Python :: 3.11
Classifier: Programming Language :: Python :: 3.12
Requires-Python: >=3.10
License-File: LICENSE
Requires-Dist: pandas
Provides-Extra: test
Requires-Dist: pytest ; extra == 'test'
